Metadata-Version: 1.1
Name: digpe
Version: 0.1.4
Summary: extract price from text
Home-page: https://github.com/ZwEin27/phone-price-extractor
Author: Lingzhe Teng
Author-email: zwein27@gmail.com
License: UNKNOWN
Download-URL: https://github.com/ZwEin27/phone-price-extractor/tarball/0.1.4
Keywords: price,extractor
Platform: UNKNOWN
